{"folk rock": ["lincoln-center-new-york", "rockwood-music-hall-new-york", "paddy-reillys-music-bar-new-york", "the-rock-shop-brooklyn", "whiskey-town-new-york"], "spoken word": ["nuyorican-poets-cafe-new-york", "shrine-new-york", "miknic-lounge-brooklyn-2", "bowery-poetry-club-new-york", "bam-caf\u00e9-brooklyn-2"], "eastern european": ["klimat-lounge-new-york", "mehanata-new-york", "scorpio-cafe-and-bar-astoria", "sly-fox-new-york"], "power pop": ["bowery-electric-new-york"], "progressive metal": ["don-pedro-brooklyn", "roseland-ballroom-new-york"], "heavy metal": ["duffs-brooklyn-brooklyn", "palace-cafe-brooklyn", "the-anchored-inn-brooklyn", "three-of-cups-lounge-new-york", "lucky-13-saloon-brooklyn"], "alternative": ["rockwood-music-hall-new-york", "fat-cat-new-york-2", "the-stone-new-york", "cafe-wha-new-york", "music-hall-of-williamsburg-brooklyn"], "korean pop": ["prince-ii-flushing", "maru-new-york", "space-billiard-caf\u00e9-new-york-2", "the-circle-nightclub-new-york", "chorus-karaoke-new-york"], "religious": ["radio-city-music-hall-new-york-2", "fat-cat-new-york-2", "shrine-new-york", "bob-bar-new-york", "prohibition-new-york"], "instrumental rock": ["bell-book-and-candle-new-york", "the-ainsworth-new-york"], "classic rock": ["minibar-brooklyn", "cafe-wha-new-york", "three-of-cups-lounge-new-york", "the-national-underground-new-york", "arlenes-grocery-new-york"], "alternative rock": ["groove-new-york", "white-noise-manhattan-2", "pianos-new-york", "fat-baby-new-york"], "lounge": ["bubble-lounge-new-york", "flatiron-lounge-new-york", "mercury-lounge-new-york", "three-of-cups-lounge-new-york", "parkside-lounge-new-york"], "nostalgia": ["rockwood-music-hall-new-york", "fat-cat-new-york-2", "tender-trap-brooklyn", "sidewalk-cafe-new-york-3", "ottos-shrunken-head-new-york"], "easy listening": ["the-path-cafe-new-york-3", "garage-restaurant-and-cafe-new-york", "cake-shop-new-york", "rogue-and-canon-new-york", "diwine-astoria"], "country pop": ["flaming-saddles-saloon-manhattan", "the-beer-garden-staten-island", "caf\u00e9-moto-brooklyn", "bourbon-street-new-york", "el-rio-grande-new-york"], "alt metal": ["three-of-cups-lounge-new-york", "pussycat-lounge-and-shogun-room-new-york"], "bass music": ["open-house-new-york", "snafu-new-york", "pop-burger-new-york", "welcome-to-the-johnsons-new-york", "langans-bar-and-restaurant-new-york"], "jazz": ["jazz-at-lincoln-center-the-allen-room-new-york-2", "smalls-new-york", "the-stone-new-york", "flatiron-room-new-york", "village-vanguard-new-york"], "quiet storm": ["misdemeanor-brooklyn", "employees-only-new-york"], "fusion": ["fat-buddha-new-york", "ugly-kitchen-new-york", "fusion-brooklyn-2", "jazz-at-kitano-new-york", "spur-tree-new-york"], "renaissance era": ["the-auction-house-new-york", "the-bourgeois-pig-new-york", "savore-ristorante-new-york"], "singer-songwriter": ["rockwood-music-hall-new-york", "the-living-room-new-york-3", "old-man-hustle-new-york-2", "petes-candy-store-brooklyn", "paddy-reillys-music-bar-new-york"], "classic r&b/soul": ["groove-new-york"], "mainstream rock": ["rodeo-bar-and-grill-new-york", "bathtub-gin-new-york", "dojo-restaurant-new-york"], "country rock": ["rockwood-music-hall-new-york", "petes-candy-store-brooklyn", "death-by-audio-brooklyn", "brooklyn-bowl-brooklyn", "rodeo-bar-and-grill-new-york"], "opera": ["lincoln-center-new-york", "ido-sushi-new-york", "bam-caf\u00e9-brooklyn-2", "carnegie-hall-new-york", "opera-nightclub-new-york-2"], "latin pop": ["mehanata-new-york", "iguana-new-york-new-york", "avel-restaurant-and-lounge-astoria", "maracas-new-york-night-club-richmond-hill"], "disco": ["rockwood-music-hall-new-york", "mehanata-new-york", "nublu-new-york", "club-shelter-new-york", "home-sweet-home-new-york"], "hardcore techno": ["cielo-new-york", "bohemian-hall-and-beer-garden-astoria", "sky-room-new-york"], "children's": ["sycamore-brooklyn-2", "carnegie-hall-new-york", "dizzys-club-coca-cola-new-york", "jazz-standard-new-york", "mercury-lounge-new-york"], "other african": ["continental-new-york-2"], "rock": ["rockwood-music-hall-new-york", "arlenes-grocery-new-york", "the-rock-shop-brooklyn", "la-kueva-2-0-latin-rock-cafe-sunnyside-2", "paddy-reillys-music-bar-new-york"], "gospel": ["bam-caf\u00e9-brooklyn-2", "dempsey-theatre-new-york", "fat-cat-new-york-2", "good-coffeehouse-music-parlor-brooklyn", "sunday-jazz-marjorie-eliots-parlour-manhattan"], "old timey": ["petes-candy-store-brooklyn", "music-hall-of-williamsburg-brooklyn", "the-way-station-brooklyn", "the-national-underground-new-york", "the-bell-house-brooklyn"], "asian": ["fat-buddha-new-york", "rockwood-music-hall-new-york", "spur-tree-new-york", "ugly-kitchen-new-york"], "pop soul": ["milk-river-brooklyn"], "classical": ["carnegie-hall-new-york", "new-york-philharmonic-new-york", "lincoln-center-new-york", "bam-caf\u00e9-brooklyn-2", "barbes-brooklyn"], "central american": ["luchos-club-woodside", "terraza-7-elmhurst-2", "the-girl-from-ipanema-new-york", "the-delancey-new-york", "wine-garden-jackson-heights"], "alternative country": ["tribeca-tavern-and-cafe-new-york", "buttermilk-bar-brooklyn", "europa-brooklyn", "pierre-loti-wine-bar-new-york"], "modern era": ["white-horse-tavern-new-york", "luceys-lounge-brooklyn"], "pacific": ["pacific-standard-brooklyn-brooklyn", "cafe-wha-new-york", "lincoln-center-new-york", "the-rock-shop-brooklyn", "4th-avenue-pub-brooklyn"], "contemporary country": ["the-duck-new-york"], "new wave": ["pyramid-club-new-york", "the-flat-new-york-2", "dark-room-new-york-2", "amaru-pisco-bar-flushing", "the-room-new-york"], "contemporary r&b": ["gagopa-karaoke-new-york", "corner-social-new-york-2"], "japanese rock": ["gramercy-theatre-new-york-2"], "blues": ["terra-blues-new-york", "the-55-bar-new-york", "arthurs-tavern-new-york", "friday-night-blues-nyc-new-york", "barbes-brooklyn"], "progressive rock": ["bar-matchless-brooklyn", "the-blind-barber-new-york", "gottino-new-york", "tortilla-flats-new-york", "karaoke-one-7-new-york"], "traditional country": ["petes-candy-store-brooklyn", "barbes-brooklyn"], "gypsy music": ["barbes-brooklyn", "mehanata-new-york", "drom-new-york", "brooklyn-fire-proof-east-brooklyn-2", "babylon-hookah-lounge-new-york"], "garage rock": ["motor-city-bar-new-york", "bowery-electric-new-york", "arthurs-tavern-new-york", "glasslands-gallery-brooklyn", "monas-new-york"], "alternative pop": ["earth-nyc-new-york"], "caribbean": ["negril-village-new-york", "spur-tree-new-york", "bembe-brooklyn", "sobs-new-york-2", "caribbean-cabana-new-york"], "house music": ["club-shelter-new-york", "cielo-new-york", "49-grove-new-york", "nublu-new-york", "falucka-new-york"], "indie rock": ["sound-fix-records-brooklyn", "the-rock-shop-brooklyn", "cake-shop-new-york", "shea-stadium-brooklyn", "music-hall-of-williamsburg-brooklyn", "sound-fix-records-brooklyn", "the-rock-shop-brooklyn", "cake-shop-new-york", "shea-stadium-brooklyn", "music-hall-of-williamsburg-brooklyn"], "new jack swing": ["bowery-poetry-club-new-york", "sway-lounge-new-york", "home-sweet-home-new-york"], "electronica": ["nublu-new-york", "bembe-brooklyn", "petes-candy-store-brooklyn", "carnegie-hall-new-york", "bowery-ballroom-new-york"], "soul jazz": ["smoke-jazz-club-new-york", "brooklyn-bowl-brooklyn", "tillmans-bar-and-lounge-new-york", "jimmys-corner-new-york"], "r&b": ["bob-bar-new-york", "groove-new-york", "the-village-underground-new-york", "freedom-party-new-york", "cafe-wha-new-york"], "doo wop": ["midway-bar-brooklyn", "post-no-bills-brooklyn", "jackies-5th-amendment-brooklyn", "town-hall-new-york", "kings-county-brooklyn-3"], "british rock": ["tropical-128-new-york", "sweet-and-vicious-new-york", "puck-fair-new-york", "the-churchill-tavern-new-york", "stout-nyc-new-york"], "meditative": ["sound-fix-lounge-brooklyn", "libation-new-york", "the-redhead-new-york"], "delta blues": ["good-coffeehouse-music-parlor-brooklyn", "terra-blues-new-york", "live-bait-new-york", "the-double-windsor-brooklyn"], "modern jazz": ["village-vanguard-new-york", "smoke-jazz-club-new-york", "zinc-bar-new-york-2", "jazz-standard-new-york", "tillmans-bar-and-lounge-new-york"], "west coast": ["pacific-standard-brooklyn-brooklyn", "the-vault-new-york", "maison-premiere-brooklyn", "roseland-ballroom-new-york", "finnertys-new-york"], "goth": ["pyramid-club-new-york", "white-noise-manhattan-2", "saint-vitus-brooklyn", "mehanata-new-york", "goodbye-blue-monday-brooklyn"], "latin": ["bembe-brooklyn", "camaradas-el-barrio-new-york", "la-kueva-2-0-latin-rock-cafe-sunnyside-2", "tio-luca-cocina-and-vino-bar-new-york", "lq-new-york"], "electric blues": ["230-fifth-new-york"], "gangsta rap": ["bizarre-brooklyn", "rocky-mcbrides-astoria", "legion-brooklyn", "the-billiard-company-forest-hills", "sheep-station-brooklyn"], "extreme metal": ["saint-vitus-brooklyn", "gramercy-theatre-new-york-2"], "middle eastern": ["egyptian-coffee-shop-astoria", "kazuza-new-york", "temple-of-ankh-new-york", "cafe-khufu-new-york"], "techno": ["club-shelter-new-york", "the-rub-brooklyn", "pacha-new-york", "tba-brooklyn-new-york", "bembe-brooklyn"], "jazz vocals": ["blue-note-new-york"], "japanese traditional": ["sake-bar-hagi-new-york"], "afrikaans": ["tolani-wine-restaurant-new-york", "sullivan-room-new-york", "kaia-wine-bar-new-york"], "other punk": ["the-library-new-york", "ottos-shrunken-head-new-york", "double-down-saloon-new-york"], "impressionism": ["l-ybane-new-york-2"], "country": ["hill-country-barbecue-market-new-york", "rockwood-music-hall-new-york", "the-patriot-saloon-new-york", "barbes-brooklyn", "the-national-underground-new-york"], "romantic era": ["lea-new-york", "prima-new-york", "oficina-latina-new-york"], "punk": ["manitobas-new-york", "the-ding-dong-lounge-new-york", "rockwood-music-hall-new-york", "cake-shop-new-york", "ottos-shrunken-head-new-york"], "himalayan": ["flatiron-room-new-york", "apoth\u00e9ke-new-york-2", "theater-bar-new-york", "highpoint-bistro-and-bar-new-york", "essex-new-york"], "folk pop": ["joes-pub-new-york", "diwine-astoria"], "pop punk": ["two-bits-retro-arcade-new-york", "molloys-irish-pub-manhattan", "ace-bar-new-york", "the-delancey-new-york", "session-73-new-york"], "americana": ["rockwood-music-hall-new-york", "barbes-brooklyn", "the-grand-victory-brooklyn", "swing-46-new-york", "fontanas-new-york"], "smooth jazz": ["the-stone-new-york", "domaine-wine-bar-long-island-city", "smoke-jazz-club-new-york", "shapeshifter-lab-brooklyn", "fat-cat-new-york-2"], "pop": ["rockwood-music-hall-new-york", "pop-burger-new-york", "paddy-reillys-music-bar-new-york", "barbes-brooklyn", "bembe-brooklyn"], "old school punk": ["duffs-brooklyn-brooklyn", "motor-city-bar-new-york", "the-library-new-york", "double-down-saloon-new-york", "iggys-keltic-lounge-new-york"], "mexican traditional": ["bann-restaurant-new-york-2"], "african pop": ["mijana-astoria-2", "xai-xai-south-african-wine-bar-new-york"], "progressive house": ["pacha-new-york", "tenjune-new-york", "le-souk-harem-new-york", "the-circle-nightclub-new-york", "one-little-west-12-new-york"], "brit pop": ["gramercy-theatre-new-york-2", "clandestino-new-york", "the-electric-room-manhattan", "the-monro-pub-brooklyn", "the-skinny-new-york"], "hard rock": ["saint-vitus-brooklyn", "arlenes-grocery-new-york", "brooklyn-bowl-brooklyn", "the-trash-bar-brooklyn", "beacon-theatre-new-york"], "latin rock": ["la-kueva-2-0-latin-rock-cafe-sunnyside-2", "d-antigua-lounge-jackson-heights", "camaradas-el-barrio-new-york", "the-bell-house-brooklyn", "amaru-pisco-bar-flushing"], "adult contemporary": ["beacon-theatre-new-york", "city-winery-new-york", "brooklyn-bowl-brooklyn", "garage-restaurant-and-cafe-new-york", "highline-ballroom-new-york"], "jam bands": ["best-buy-theater-new-york", "brooklyn-bowl-brooklyn", "beacon-theatre-new-york", "sullivan-hall-new-york", "triad-theatre-new-york"], "klezmer": ["city-winery-new-york", "barbes-brooklyn", "caf\u00e9-moto-brooklyn", "bierhaus-nyc-new-york", "la-birreria-new-york"], "pakistani": ["birdland-new-york", "bamiyan-new-york", "sycamore-brooklyn-2", "khyber-pass-restaurant-new-york", "tenjune-new-york"], "reggaeton": ["bembe-brooklyn", "parlay-bar-ridgewood", "agua-roja-hookah-bar-and-lounge-manhattan", "babel-nyc-new-york", "la-linea-new-york"], "grunge": ["petes-candy-store-brooklyn", "bowery-ballroom-new-york", "bowery-electric-new-york", "bob-bar-new-york", "goodbye-blue-monday-brooklyn"], "korean traditional": ["maru-new-york"], "jewish": ["museum-at-eldridge-street-new-york", "barbes-brooklyn", "petes-candy-store-brooklyn", "bob-bar-new-york", "cake-shop-new-york"], "environmental": ["hypnotic-brass-ensemble-new-york", "cake-shop-new-york", "alice-tully-hall-new-york", "bembe-brooklyn", "pyramid-club-new-york"], "central european": ["radegast-hall-and-biergarten-brooklyn", "bohemian-hall-and-beer-garden-astoria", "botanica-bar-new-york", "cloister-cafe-new-york", "prime-meats-brooklyn"], "chinese pop": ["k-one-new-york"], "karaoke": ["karaoke-duet-53-new-york", "baby-grand-new-york", "inhabit-karaoke-lounge-new-york", "gagopa-karaoke-new-york"], "funk": ["rockwood-music-hall-new-york", "bembe-brooklyn", "nublu-new-york", "the-village-underground-new-york", "cafe-wha-new-york"], "christmas": ["radio-city-music-hall-new-york-2", "rockwood-music-hall-new-york", "nublu-new-york", "petes-candy-store-brooklyn", "cake-shop-new-york"], "brit rock": ["fiddlesticks-new-york", "home-sweet-home-new-york"], "scandinavian": ["white-slab-palace-new-york", "new-york-philharmonic-new-york", "richlane-brooklyn-2", "rue-b-new-york"], "dancehall reggae": ["the-base-nightclub-brooklyn", "the-rub-brooklyn", "tammany-hall-new-york", "sobs-new-york-2", "rooftop-760-new-york"], "roots reggae": ["happy-ending-new-york", "spur-tree-new-york", "lit-lounge-new-york", "swift-new-york"], "japanese pop": ["best-buy-theater-new-york", "fish-bar-new-york", "karaoke-st-marks-manhattan", "keybar-new-york"], "industrial": ["pyramid-club-new-york", "bam-caf\u00e9-brooklyn-2", "the-bell-house-brooklyn", "fat-cat-new-york-2", "the-anchored-inn-brooklyn"], "indie pop": ["the-living-room-new-york-3", "saint-vitus-brooklyn", "spike-hill-brooklyn", "b61-brooklyn", "mercury-lounge-new-york"], "avant garde": ["the-stone-new-york", "issue-project-room-brooklyn", "tio-luca-cocina-and-vino-bar-new-york", "barbes-brooklyn", "nublu-new-york"], "european pop": ["club-21-astoria"], "bluegrass": ["sunnys-bar-brooklyn", "paddy-reillys-music-bar-new-york", "rockwood-music-hall-new-york", "flatiron-room-new-york", "monas-new-york"], "australasian": ["the-daily-new-york"], "mixtape": ["gotham-comedy-club-new-york", "the-library-new-york", "the-magician-new-york", "webster-hall-new-york"], "west african": ["rockwood-music-hall-new-york", "shrine-new-york", "buka-new-york-brooklyn", "mataheko-jamaica", "barbes-brooklyn"], "rap": ["bob-bar-new-york", "groove-new-york", "music-hall-of-williamsburg-brooklyn", "radio-city-music-hall-new-york-2"], "baroque era": ["miller-theatre-new-york"], "south american": ["terraza-7-elmhurst-2", "desnuda-new-york-2", "bembe-brooklyn", "nights-and-weekends-brooklyn"], "neo-soul": ["bembe-brooklyn", "tillmans-bar-and-lounge-new-york", "the-village-underground-new-york", "sobs-new-york-2"], "cool jazz": ["fat-cat-new-york-2", "zinc-bar-new-york-2", "birdland-new-york", "american-legion-post-398-new-york", "blue-note-new-york"], "alternative dance": ["pyramid-club-new-york", "lit-lounge-new-york", "qxts-newark"], "game music": ["von-new-york", "the-irish-pub-new-york", "the-liberty-new-york"], "latin dance": ["bembe-brooklyn", "club-cache-new-york", "sobs-new-york-2", "iguana-new-york-new-york"], "doom metal": ["saint-vitus-brooklyn", "the-trash-bar-brooklyn"], "surf rock": ["ottos-shrunken-head-new-york", "city-winery-new-york", "double-down-saloon-new-york", "pkny-new-york"], "new age": ["the-way-station-brooklyn", "l-i-c-bar-long-island-city", "le-poisson-rouge-new-york", "jazz-standard-new-york", "dominies-astoria"], "british isles": ["wilfie-and-nell-new-york", "the-cricketers-arms-new-york", "the-red-lion-new-york", "the-thirsty-scholar-new-york", "alphabet-city-beer-co-new-york-2"], "post-punk": ["c-squat-new-york", "don-pedro-brooklyn", "le-poisson-rouge-new-york", "pianos-new-york", "drom-new-york"], "animation": ["brooklyn-bowl-brooklyn", "flatiron-room-new-york", "2a-new-york", "public-assembly-brooklyn", "bar-matchless-brooklyn"], "other pop": ["pop-pub-new-york", "baby-grand-new-york", "pop-burger-new-york", "butter-restaurant-new-york"], "comedy": ["comedy-cellar-new-york", "upright-citizens-brigade-theatre-new-york-4", "gotham-comedy-club-new-york", "peoples-improv-theater-new-york"], "bebop": ["village-vanguard-new-york", "fat-cat-new-york-2", "bills-place-new-york", "arthurs-tavern-new-york"], "reggae": ["bembe-brooklyn", "bob-bar-new-york", "shrine-new-york", "la-linea-new-york", "cafe-wha-new-york"], "traditional": ["paddy-reillys-music-bar-new-york", "barbes-brooklyn", "petes-candy-store-brooklyn", "brooklyn-bowl-brooklyn", "cafe-wha-new-york"], "club dance": ["club-57-corp-new-york", "the-central-bar-new-york", "metronome-hospitality-group-new-york", "brownstone-lounge-manhattan", "the-woods-brooklyn"], "soundtrack": ["fat-cat-new-york-2", "terraza-7-elmhurst-2", "bob-bar-new-york", "cake-shop-new-york", "dark-room-new-york-2"], "mexican pop": ["la-cucina-mexican-grill-and-cantina-bar-brooklyn", "taqueria-lower-east-side-new-york"], "early jazz": ["bar-next-door-manhattan", "barbes-brooklyn", "jazz-standard-new-york", "54-below-new-york", "radegast-hall-and-biergarten-brooklyn"], "rockabilly": ["ottos-shrunken-head-new-york", "barbes-brooklyn", "rodeo-bar-and-grill-new-york", "union-pool-brooklyn-2", "hanks-saloon-brooklyn"], "psychedelic": ["barbes-brooklyn", "shrine-new-york", "polish-national-home-brooklyn-2", "the-freak-bar-new-york"], "celtic": ["paddy-reillys-music-bar-new-york", "celtic-gasthaus-glendale", "playwright-celtic-pub-new-york", "duffs-brooklyn-brooklyn", "irish-haven-brooklyn"], "southern african": ["buka-new-york-brooklyn"], "metal": ["duffs-brooklyn-brooklyn", "saint-vitus-brooklyn", "lucky-13-saloon-brooklyn", "the-anchored-inn-brooklyn", "palace-cafe-brooklyn"], "contemporary jazz": ["birdland-new-york", "jazz-standard-new-york", "city-winery-new-york"], "gothic metal": ["qxts-newark"], "north african": ["shalel-lounge-new-york", "barbes-brooklyn", "carthage-521-brooklyn", "arabesque-new-york-2", "le-souk-harem-new-york"], "southern rap": ["the-skinny-new-york", "the-woods-brooklyn"], "trance": ["pacha-new-york", "electric-zoo-festival-new-york-3", "bembe-brooklyn", "sullivan-room-new-york", "babel-nyc-new-york"], "dance pop": ["monster-new-york", "the-delancey-new-york", "webster-hall-new-york", "solas-new-york"], "show tunes": ["maries-crisis-new-york", "monster-new-york", "the-duplex-new-york", "brandys-piano-bar-new-york", "therapy-new-york"]}